[
    {
        "label": "tensorflow",
        "kind": 6,
        "isExtraImport": true,
        "importPath": "tensorflow",
        "description": "tensorflow",
        "detail": "tensorflow",
        "documentation": {}
    },
    {
        "label": "Flask",
        "importPath": "flask",
        "description": "flask",
        "isExtraImport": true,
        "detail": "flask",
        "documentation": {}
    },
    {
        "label": "request",
        "importPath": "flask",
        "description": "flask",
        "isExtraImport": true,
        "detail": "flask",
        "documentation": {}
    },
    {
        "label": "jsonify",
        "importPath": "flask",
        "description": "flask",
        "isExtraImport": true,
        "detail": "flask",
        "documentation": {}
    }
]